src/__init__.py
srcds-0.0.1.dist-info/METADATA
srcds-0.0.1.dist-info/WHEEL
srcds-0.0.1.dist-info/top_level.txt
srcds-0.0.1.dist-info/RECORD
